blockcoins/__init__.py
blockcoins/blockcoins.py
blockcoins-0.2.1.dist-info/licenses/LICENSE
blockcoins-0.2.1.dist-info/METADATA
blockcoins-0.2.1.dist-info/WHEEL
blockcoins-0.2.1.dist-info/top_level.txt
blockcoins-0.2.1.dist-info/RECORD
