Metadata-Version: 2.4
Name: blockcoins
Version: 0.2.1
Summary: A bot to automatically farm BlockCoins on blockcoin.vercel.app
Author-email: Vegeta <Gamma.scratch@gmail.com>
License: MIT
License-File: LICENSE
Requires-Dist: blockcoin
Dynamic: license-file
